doc_wizard/__main__.py
doc_wizard/doc.py
doc_wizard/gitlab_ci.py
doc_wizard-1.0.1.dist-info/METADATA
doc_wizard-1.0.1.dist-info/WHEEL
doc_wizard-1.0.1.dist-info/entry_points.txt
doc_wizard-1.0.1.dist-info/top_level.txt
doc_wizard-1.0.1.dist-info/RECORD
