Metadata-Version: 2.1
Name: doc-wizard
Version: 1.0.1
Summary: A prospective zmq-i2c server replacement
Home-page: https://gitlab.cern.ch/jtrielof/doc-wizard.git
Author: Jonathan Trieloff
Author-email: j.trieloff@cern.ch
License: MIT
Platform: UNKNOWN
Classifier: License :: OSI Approved :: MIT License
Classifier: Programming Language :: Python :: 3
Classifier: Programming Language :: Python :: 3.7
Requires-Dist: typing
Requires-Dist: click
